daqopen/__init__.py
daqopen/channelbuffer.py
daqopen/daqinfo.py
daqopen/daqzmq.py
daqopen/duedaq.py
daqopen/helper.py
daqopen_lib-0.7.2.dist-info/METADATA
daqopen_lib-0.7.2.dist-info/WHEEL
daqopen_lib-0.7.2.dist-info/licenses/LICENSE
daqopen_lib-0.7.2.dist-info/RECORD
