Metadata-Version: 2.4
Name: daqopen-lib
Version: 0.7.2
Summary: A data acquisition library for streaming adc data from arduino due and more
Project-URL: Homepage, https://github.com/DaqOpen/daqopen-lib
Project-URL: Issues, https://github.com/DaqOpen/daqopen-lib/issues
Author-email: Michael Oberhofer <michael@daqopen.com>
License-File: LICENSE
Classifier: License :: OSI Approved :: MIT License
Classifier: Operating System :: OS Independent
Classifier: Programming Language :: Python :: 3
Requires-Python: >=3.11
Requires-Dist: numpy
Requires-Dist: pyserial
Requires-Dist: zmq
